scutout/__init__.py
scutout/config.py
scutout/cutout_extractor.py
scutout/utils.py
scutout-1.0.3.data/scripts/run_scutout.py
scutout-1.0.3.dist-info/LICENSE
scutout-1.0.3.dist-info/METADATA
scutout-1.0.3.dist-info/WHEEL
scutout-1.0.3.dist-info/top_level.txt
scutout-1.0.3.dist-info/RECORD
