Metadata-Version: 2.1
Name: scutout
Version: 1.0.3
Summary: Tool to extract source cutouts from a collection of astronomical FITS images
Home-page: https://github.com/SKA-INAF/scutout
Author: Simone Riggi
Author-email: simone.riggi@gmail.com
License: GPL3
Download-URL: https://github.com/user/reponame/archive/v1.0.0.tar.gz
Keywords: source,cutout,survey
Platform: UNKNOWN
Classifier: Development Status :: 5 - Production/Stable
Classifier: Intended Audience :: Science/Research
Classifier: Topic :: Scientific/Engineering :: Astronomy
Classifier: License :: OSI Approved :: GNU General Public License v3 (GPLv3)
Classifier: Programming Language :: Python :: 3
License-File: LICENSE
Requires-Dist: numpy (>=1.10)
Requires-Dist: astropy
Requires-Dist: montage-wrapper
Requires-Dist: radio-beam
Requires-Dist: regions
Requires-Dist: scipy
Requires-Dist: pyparsing
